piqok/__init__.py
piqok/piqok.py
piqok/test_piqok.py
piqok-0.0.7.dist-info/LICENSE
piqok-0.0.7.dist-info/METADATA
piqok-0.0.7.dist-info/WHEEL
piqok-0.0.7.dist-info/entry_points.txt
piqok-0.0.7.dist-info/top_level.txt
piqok-0.0.7.dist-info/RECORD
