Metadata-Version: 2.1
Name: piqok
Version: 0.0.7
Summary: Get help with json
Home-page: https://github.com/piqok/piqok
Author: Gilad Kutiel
Author-email: gilad.kutiel@gmail.com
License: UNKNOWN
Platform: UNKNOWN
Classifier: Programming Language :: Python :: 3
Classifier: License :: OSI Approved :: MIT License
Classifier: Operating System :: OS Independent
Requires-Python: >=3.6
